pyenvinfo/__init__.py
pyenvinfo/__main__.py
pyenvinfo/__version__.py
pyenvinfo/py.typed
pyenvinfo-0.0.1.dist-info/LICENSE
pyenvinfo-0.0.1.dist-info/METADATA
pyenvinfo-0.0.1.dist-info/WHEEL
pyenvinfo-0.0.1.dist-info/top_level.txt
pyenvinfo-0.0.1.dist-info/RECORD
