Metadata-Version: 2.1
Name: pyenvinfo
Version: 0.0.1
Summary: DESCRIPTION
Home-page: https://github.com/thombashi/pyenvinfo
Author: Tsuyoshi Hombashi
Author-email: tsuyoshi.hombashi@gmail.com
License: MIT License
Project-URL: Documentation, https://pyenvinfo.rtfd.io/
Project-URL: Source, https://github.com/thombashi/pyenvinfo
Project-URL: Tracker, https://github.com/thombashi/pyenvinfo/issues
Platform: UNKNOWN
Classifier: Development Status :: 3 - Alpha
Classifier: Intended Audience :: Developers
Classifier: Intended Audience :: Information Technology
Classifier: License :: OSI Approved :: MIT License
Classifier: Operating System :: OS Independent
Classifier: Programming Language :: Python :: 3
Classifier: Programming Language :: Python :: 3.5
Classifier: Programming Language :: Python :: 3.6
Classifier: Programming Language :: Python :: 3.7
Classifier: Programming Language :: Python :: 3.8
Classifier: Programming Language :: Python :: 3.9
Classifier: Programming Language :: Python :: 3 :: Only
Classifier: Programming Language :: Python :: Implementation :: CPython
Classifier: Programming Language :: Python :: Implementation :: PyPy
Classifier: Topic :: Software Development :: Libraries
Classifier: Topic :: Software Development :: Libraries :: Python Modules
Requires-Python: >=3.5
Provides-Extra: test
Requires-Dist: pytest (>=6.0.1) ; extra == 'test'
Requires-Dist: pytest-discord (>=0.0.5) ; extra == 'test'
Requires-Dist: pytest-md-report (>=0.1) ; extra == 'test'
